Metadata-Version: 2.1
Name: sentry-dingtalk-metaapp
Version: 1.0.13
Summary: sentry extension which can send error to ding-talk.
Home-page: https://github.com/linchengzzz/sentry-dingtalk-metaapp
Author: Linchengzzz
Author-email: 1139489076@qq.com
License: GPL License
Keywords: Sentry DingTalk MetaApp
Platform: UNKNOWN
Classifier: Framework :: Django
Classifier: Intended Audience :: Developers
Classifier: Operating System :: OS Independent
Classifier: Natural Language :: Chinese (Simplified)
Classifier: Programming Language :: Python :: 2.7
Classifier: License :: OSI Approved :: GNU General Public License v3 (GPLv3)
